dpdktest
