Metadata-Version: 1.1
Name: dpdktest
Version: 0.1.1
Summary: Tool to test if your NIC is supported by DPDK framework.
Home-page: https://github.com/povilasb/dpdktest
Author: Povilas Balciunas
Author-email: balciunas90@gmail.com
License: MIT
Platform: UNKNOWN
Classifier: Programming Language :: Python :: 3.4
Classifier: Programming Language :: Python :: 3.5
Classifier: Operating System :: POSIX :: Linux
Classifier: Natural Language :: English
Classifier: Development Status :: 3 - Alpha
